pytalog/pd/__init__.py
pytalog/pd/data_sources/__init__.py
pytalog/pd/data_sources/df.py
pytalog/pd/data_sources/file.py
pytalog/pd/data_sources/sql.py
pytalog_pandas-0.1.1.dist-info/METADATA
pytalog_pandas-0.1.1.dist-info/WHEEL
pytalog_pandas-0.1.1.dist-info/top_level.txt
pytalog_pandas-0.1.1.dist-info/RECORD
