Metadata-Version: 2.1
Name: pytalog-pandas
Version: 0.1.1
Requires-Dist: pytalog-base==0.1.1
Requires-Dist: pandas>=1.5.0
Requires-Dist: openpyxl>=3.1.2
Requires-Dist: pyarrow>=14.0.1
Requires-Dist: numpy<2.0
Provides-Extra: dev
Requires-Dist: pytalog-base==0.1.1; extra == "dev"
Requires-Dist: pandas==1.5.0; extra == "dev"
Requires-Dist: openpyxl==3.1.2; extra == "dev"
Requires-Dist: pyarrow==14.0.1; extra == "dev"
Requires-Dist: numpy<2.0; extra == "dev"
Provides-Extra: strict
Requires-Dist: pytalog-base==0.1.1; extra == "strict"
Requires-Dist: pandas==1.5.0; extra == "strict"
Requires-Dist: openpyxl==3.1.2; extra == "strict"
Requires-Dist: pyarrow==14.0.1; extra == "strict"
Requires-Dist: numpy<2.0; extra == "strict"
